fastsafetensors/__init__.py
fastsafetensors/common.py
fastsafetensors/cpp.cpython-39-x86_64-linux-gnu.so
fastsafetensors/cpp.pyi
fastsafetensors/dlpack.py
fastsafetensors/file_buffer.py
fastsafetensors/loader.py
fastsafetensors/parallel_loader.py
fastsafetensors/st_types.py
fastsafetensors/tensor_factory.py
fastsafetensors/copier/base.py
fastsafetensors/copier/example_copier.py
fastsafetensors/copier/gds.py
fastsafetensors/copier/nogds.py
fastsafetensors/cpp/cuda_compat.h
fastsafetensors/cpp/ext.cpp
fastsafetensors/cpp/ext.hpp
fastsafetensors/frameworks/__init__.py
fastsafetensors/frameworks/_paddle.py
fastsafetensors/frameworks/_torch.py
fastsafetensors-0.2.0.dist-info/licenses/LICENSE
fastsafetensors-0.2.0.dist-info/METADATA
fastsafetensors-0.2.0.dist-info/WHEEL
fastsafetensors-0.2.0.dist-info/top_level.txt
fastsafetensors-0.2.0.dist-info/RECORD
