Metadata-Version: 2.4
Name: fastsafetensors
Version: 0.2.0
Summary: High-performance safetensors model loader
Author-email: Takeshi Yoshimura <tyos@jp.ibm.com>
Maintainer-email: Takeshi Yoshimura <tyos@jp.ibm.com>
License: Apache-2.0
Project-URL: Repository, https://github.com/foundation-model-stack/fastsafetensors
Keywords: fastsafetensors,safetensors,GDS
Requires-Python: >=3.9
License-File: LICENSE
Requires-Dist: typer>=0.9.0
Provides-Extra: test
Requires-Dist: torch>=2.5.1; extra == "test"
Requires-Dist: pytest>=8.1.1; extra == "test"
Requires-Dist: pytest-cov>=5.0.0; extra == "test"
Requires-Dist: transformers>=4.40.2; extra == "test"
Requires-Dist: safetensors>=0.4.0; extra == "test"
Requires-Dist: vllm>=0.8.2; extra == "test"
Dynamic: license-file
